helloworld_test_rv.py
helloworld_test_rv-0.0.1.dist-info/METADATA
helloworld_test_rv-0.0.1.dist-info/WHEEL
helloworld_test_rv-0.0.1.dist-info/top_level.txt
helloworld_test_rv-0.0.1.dist-info/RECORD
